bdwp/__init__.py
bdwp/cli_parse.py
bdwp/core.py
bdwp/utils.py
bdwp/__metadata__/DISCLAIMER.md
bdwp/__metadata__/LICENSE
bdwp/__metadata__/README.md
bdwp/__metadata__/__init__.py
bdwp/__metadata__/requirements.txt
bdwp/pkg_data/darwin/__init__.py
bdwp/pkg_data/darwin/express/__init__.py
bdwp/pkg_data/darwin/express/express.py
bdwp/pkg_data/darwin/express/pytransform.so
bdwp/pkg_data/darwin/obf/__init__.py
bdwp/pkg_data/darwin/obf/obf.py
bdwp/pkg_data/darwin/obf/pytransform.so
bdwp/pkg_data/linux/__init__.py
bdwp/pkg_data/linux/express/__init__.py
bdwp/pkg_data/linux/express/express.py
bdwp/pkg_data/linux/express/pytransform.so
bdwp/pkg_data/linux/obf/__init__.py
bdwp/pkg_data/linux/obf/obf.py
bdwp/pkg_data/linux/obf/pytransform.so
bdwp/pkg_data/windows/__init__.py
bdwp/pkg_data/windows/express/__init__.py
bdwp/pkg_data/windows/express/express.py
bdwp/pkg_data/windows/express/pytransform.pyd
bdwp/pkg_data/windows/obf/__init__.py
bdwp/pkg_data/windows/obf/obf.py
bdwp/pkg_data/windows/obf/pytransform.pyd
bdwp-0.0.15.dist-info/METADATA
bdwp-0.0.15.dist-info/WHEEL
bdwp-0.0.15.dist-info/top_level.txt
bdwp-0.0.15.dist-info/RECORD
